{
  "app_settings": [
    "created_at",
    "description",
    "key",
    "updated_at",
    "value"
  ],
  "command_responses": [
    "command_id",
    "created_at",
    "id",
    "response"
  ],
  "component_definitions": [
    "created_at",
    "datasheet_url",
    "default_parameters",
    "id",
    "name",
    "part_number",
    "type",
    "updated_at",
    "vendor"
  ],
  "component_parameter_definitions": [
    "component_definition_id",
    "created_at",
    "default_max",
    "default_min",
    "description",
    "id",
    "is_writable",
    "name",
    "unit",
    "updated_at"
  ],
  "component_parameters": [
    "component_id",
    "created_at",
    "current_value",
    "data_type",
    "definition_id",
    "id",
    "is_writable",
    "max_value",
    "min_value",
    "read_modbus_address",
    "read_modbus_type",
    "set_value",
    "show_in_graph",
    "show_in_ui",
    "updated_at",
    "write_modbus_address",
    "write_modbus_type"
  ],
  "component_parameters_full": [
    "component_id",
    "component_name",
    "component_type",
    "created_at",
    "current_value",
    "data_type",
    "definition_id",
    "description",
    "id",
    "is_writable",
    "machine_id",
    "machine_serial",
    "max_value",
    "min_value",
    "parameter_name",
    "read_modbus_address",
    "read_modbus_type",
    "set_value",
    "show_in_graph",
    "show_in_ui",
    "unit",
    "updated_at",
    "write_modbus_address",
    "write_modbus_type"
  ],
  "experiment_metadata": [
    "created_at",
    "environmental_conditions",
    "equipment_settings",
    "experiment_id",
    "id",
    "parameter_tolerances",
    "parameter_units",
    "quality_threshold",
    "substrate_info"
  ],
  "experiment_results": [
    "created_at",
    "critical_deviations",
    "experiment_id",
    "id",
    "measurements",
    "observations",
    "parameter_deviations",
    "quality_metrics",
    "quality_score",
    "recommendations"
  ],
  "experiments": [
    "created_at",
    "end_time",
    "id",
    "machine_id",
    "notes",
    "operator_id",
    "process_execution_id",
    "recipe_version",
    "start_time",
    "status",
    "updated_at"
  ],
  "loop_step_config": [
    "created_at",
    "id",
    "iteration_count",
    "step_id",
    "updated_at"
  ],
  "machine_components": [
    "created_at",
    "definition_id",
    "id",
    "is_activated",
    "is_persistent",
    "machine_id",
    "name",
    "type",
    "updated_at"
  ],
  "machine_health": [
    "created_at",
    "id",
    "machine_id",
    "plc_connected",
    "plc_error",
    "plc_last_check",
    "plc_last_connected",
    "plc_reconnect_attempts",
    "realtime_connected",
    "realtime_error",
    "realtime_last_check",
    "realtime_last_message",
    "updated_at"
  ],
  "machine_state": [
    "current_state",
    "failure_component",
    "failure_description",
    "is_failure_mode",
    "machine_id",
    "process_id",
    "state_since",
    "updated_at"
  ],
  "machines": [
    "admin_id",
    "created_at",
    "current_operator_id",
    "current_process_id",
    "id",
    "install_date",
    "is_active",
    "is_virtual",
    "lab_institution",
    "lab_name",
    "last_maintenance_date",
    "location",
    "machine_type",
    "model",
    "serial_number",
    "status",
    "updated_at",
    "virtual_config"
  ],
  "maintenance_records": [
    "attachments",
    "component_id",
    "created_at",
    "description",
    "id",
    "machine_id",
    "maintenance_type",
    "next_maintenance_date",
    "notes",
    "performed_at",
    "performed_by",
    "schedule_id"
  ],
  "maintenance_schedule": [
    "component_id",
    "created_at",
    "frequency_days",
    "id",
    "last_performed",
    "machine_id",
    "maintenance_type",
    "next_due",
    "updated_at"
  ],
  "migration_audit": [
    "executed_at",
    "id",
    "migration_name",
    "records_affected"
  ],
  "operator_sessions": [
    "created_at",
    "end_time",
    "id",
    "machine_id",
    "operator_id",
    "start_time",
    "status",
    "updated_at"
  ],
  "parameter_control_commands": [
    "completed_at",
    "created_at",
    "error_message",
    "executed_at",
    "id",
    "machine_id",
    "parameter_name",
    "target_value",
    "timeout_ms"
  ],
  "parameter_step_config": [
    "adjustment_rate",
    "created_at",
    "hold_duration_ms",
    "id",
    "parameter_id",
    "step_id",
    "target_value",
    "updated_at"
  ],
  "parameter_value_history": [
    "created_at",
    "id",
    "parameter_id",
    "set_point",
    "timestamp",
    "value"
  ],
  "process_data_points": [
    "created_at",
    "id",
    "parameter_id",
    "process_id",
    "set_point",
    "timestamp",
    "value"
  ],
  "process_execution_state": [
    "created_at",
    "current_loop_count",
    "current_loop_iteration",
    "current_overall_step",
    "current_parameter_id",
    "current_parameter_value",
    "current_purge_duration_ms",
    "current_step",
    "current_step_index",
    "current_step_name",
    "current_step_type",
    "current_valve_duration_ms",
    "current_valve_number",
    "execution_id",
    "id",
    "last_updated",
    "process_metrics",
    "progress",
    "total_overall_steps"
  ],
  "process_executions": [
    "created_at",
    "description",
    "end_time",
    "error_message",
    "id",
    "machine_id",
    "operator_id",
    "parameters",
    "recipe_id",
    "recipe_version",
    "session_id",
    "start_time",
    "status",
    "updated_at"
  ],
  "profiles": [
    "avatar_url",
    "created_at",
    "email",
    "full_name",
    "id",
    "legacy_role",
    "migrated_at",
    "phone",
    "role",
    "role_id",
    "status",
    "updated_at",
    "username"
  ],
  "purge_step_config": [
    "created_at",
    "duration_ms",
    "flow_rate",
    "gas_type",
    "id",
    "step_id",
    "updated_at"
  ],
  "recipe_commands": [
    "created_at",
    "error_message",
    "executed_at",
    "id",
    "machine_id",
    "parameters",
    "recipe_step_id",
    "status",
    "type",
    "updated_at"
  ],
  "recipe_parameters": [
    "created_at",
    "id",
    "is_critical",
    "max_value",
    "min_value",
    "parameter_name",
    "parameter_type",
    "parameter_unit",
    "parameter_value",
    "recipe_id",
    "tolerance_percentage",
    "updated_at"
  ],
  "recipe_step_configs_archive": [
    "archive_reason",
    "archived_at",
    "config",
    "created_at",
    "description",
    "original_table_name",
    "parent_step_id",
    "recipe_id",
    "sequence_number",
    "step_id",
    "step_name",
    "step_type"
  ],
  "recipe_steps": [
    "created_at",
    "description",
    "id",
    "name",
    "parent_step_id",
    "recipe_id",
    "sequence_number",
    "type"
  ],
  "recipes": [
    "chamber_temperature_set_point",
    "created_at",
    "created_by",
    "description",
    "id",
    "is_public",
    "machine_type",
    "name",
    "pressure_set_point",
    "substrate",
    "updated_at",
    "version"
  ],
  "step_execution_history": [
    "created_at",
    "ended_at",
    "id",
    "parameters",
    "process_id",
    "started_at",
    "step_name",
    "step_number",
    "step_type"
  ],
  "user_machine_assignments": [
    "assigned_at",
    "assigned_by",
    "created_at",
    "id",
    "is_active",
    "machine_id",
    "permissions",
    "role",
    "updated_at",
    "user_id"
  ],
  "user_machine_preferences": [
    "created_at",
    "current_machine_id",
    "id",
    "last_switched_at",
    "preferences",
    "updated_at",
    "user_id"
  ],
  "user_roles": [
    "created_at",
    "description",
    "display_name",
    "hierarchy_level",
    "id",
    "is_active",
    "name",
    "permissions",
    "updated_at"
  ],
  "valve_step_config": [
    "created_at",
    "duration_ms",
    "id",
    "step_id",
    "updated_at",
    "valve_id",
    "valve_number"
  ],
  "virtual_machine_server_status": [
    "id",
    "last_ping",
    "metadata",
    "status",
    "updated_at"
  ]
}
